tensorrt_yolo/__init__.py
tensorrt_yolo/cli.py
tensorrt_yolo/export/__init__.py
tensorrt_yolo/export/head.py
tensorrt_yolo/export/ppyoloe.py
tensorrt_yolo/infer/__init__.py
tensorrt_yolo/infer/model.py
tensorrt_yolo/infer/utils.py
tensorrt_yolo/libs/__init__.py
tensorrt_yolo_isarsoft-6.2.0.dist-info/METADATA
tensorrt_yolo_isarsoft-6.2.0.dist-info/WHEEL
tensorrt_yolo_isarsoft-6.2.0.dist-info/entry_points.txt
tensorrt_yolo_isarsoft-6.2.0.dist-info/top_level.txt
tensorrt_yolo_isarsoft-6.2.0.dist-info/RECORD
